[1,["181ee3b80@6c48a"],["_textureSource"],["cc.SpriteFrame","cc.SpriteAtlas"],0,[[[{"name":"01-arm1","rect":{"x":753,"y":559,"width":132,"height":152},"offset":{"x":0,"y":0},"originalSize":{"width":132,"height":152},"rotated":false,"capInsets":[0,0,0,0],"packable":true,"pixelsToUnit":100,"pivot":{"x":0.5,"y":0.5},"meshType":0}],[0],0,[0],[0],[0]],[[{"name":"07-head1","rect":{"x":569,"y":382,"width":275,"height":171},"offset":{"x":0,"y":0},"originalSize":{"width":275,"height":171},"rotated":false,"capInsets":[0,0,0,0],"packable":true,"pixelsToUnit":100,"pivot":{"x":0.5,"y":0.5},"meshType":0}],[0],0,[0],[0],[0]],[[{"name":"04-ear1","rect":{"x":406,"y":566,"width":153,"height":161},"offset":{"x":0,"y":0},"originalSize":{"width":153,"height":161},"rotated":false,"capInsets":[0,0,0,0],"packable":true,"pixelsToUnit":100,"pivot":{"x":0.5,"y":0.5},"meshType":0}],[0],0,[0],[0],[0]],[[{"name":"02-arm2","rect":{"x":283,"y":875,"width":117,"height":126},"offset":{"x":0,"y":0},"originalSize":{"width":117,"height":126},"rotated":false,"capInsets":[0,0,0,0],"packable":true,"pixelsToUnit":100,"pivot":{"x":0.5,"y":0.5},"meshType":0}],[0],0,[0],[0],[0]],[[{"name":"03-body","rect":{"x":3,"y":382,"width":308,"height":274},"offset":{"x":0,"y":0},"originalSize":{"width":308,"height":274},"rotated":true,"capInsets":[0,0,0,0],"packable":true,"pixelsToUnit":100,"pivot":{"x":0.5,"y":0.5},"meshType":0}],[0],0,[0],[0],[0]],[[{"name":"08-leg1","rect":{"x":283,"y":698,"width":109,"height":100},"offset":{"x":0,"y":0},"originalSize":{"width":109,"height":100},"rotated":false,"capInsets":[0,0,0,0],"packable":true,"pixelsToUnit":100,"pivot":{"x":0.5,"y":0.5},"meshType":0}],[0],0,[0],[0],[0]],[[{"name":"02-arm2","rect":{"x":283,"y":566,"width":117,"height":126},"offset":{"x":0,"y":0},"originalSize":{"width":117,"height":126},"rotated":false,"capInsets":[0,0,0,0],"packable":true,"pixelsToUnit":100,"pivot":{"x":0.5,"y":0.5},"meshType":0}],[0],0,[0],[0],[0]],[[{"name":"06-head","rect":{"x":3,"y":3,"width":409,"height":373},"offset":{"x":0,"y":0},"originalSize":{"width":409,"height":373},"rotated":false,"capInsets":[0,0,0,0],"packable":true,"pixelsToUnit":100,"pivot":{"x":0.5,"y":0.5},"meshType":0}],[0],0,[0],[0],[0]],[[{"name":"07-head1","rect":{"x":283,"y":382,"width":280,"height":178},"offset":{"x":-0.5,"y":0},"originalSize":{"width":281,"height":178},"rotated":false,"capInsets":[0,0,0,0],"packable":true,"pixelsToUnit":100,"pivot":{"x":0.5,"y":0.5},"meshType":0}],[0],0,[0],[0],[0]],[[{"name":"04-ear1","rect":{"x":590,"y":847,"width":153,"height":161},"offset":{"x":0,"y":0},"originalSize":{"width":153,"height":161},"rotated":false,"capInsets":[0,0,0,0],"packable":true,"pixelsToUnit":100,"pivot":{"x":0.5,"y":0.5},"meshType":0}],[0],0,[0],[0],[0]],[[{"name":"03-body","rect":{"x":3,"y":696,"width":308,"height":274},"offset":{"x":0,"y":0},"originalSize":{"width":308,"height":274},"rotated":true,"capInsets":[0,0,0,0],"packable":true,"pixelsToUnit":100,"pivot":{"x":0.5,"y":0.5},"meshType":0}],[0],0,[0],[0],[0]],[[{"name":"06-head","rect":{"x":418,"y":3,"width":409,"height":373},"offset":{"x":0,"y":0},"originalSize":{"width":409,"height":373},"rotated":false,"capInsets":[0,0,0,0],"packable":true,"pixelsToUnit":100,"pivot":{"x":0.5,"y":0.5},"meshType":0}],[0],0,[0],[0],[0]],[[{"name":"09-leg2","rect":{"x":504,"y":733,"width":108,"height":97},"offset":{"x":0,"y":0},"originalSize":{"width":108,"height":97},"rotated":true,"capInsets":[0,0,0,0],"packable":true,"pixelsToUnit":100,"pivot":{"x":0.5,"y":0.5},"meshType":0}],[0],0,[0],[0],[0]],[[{"name":"05-ear2","rect":{"x":569,"y":559,"width":168,"height":178},"offset":{"x":0,"y":0},"originalSize":{"width":168,"height":178},"rotated":true,"capInsets":[0,0,0,0],"packable":true,"pixelsToUnit":100,"pivot":{"x":0.5,"y":0.5},"meshType":0}],[0],0,[0],[0],[0]],[[{"name":"10-tail","rect":{"x":749,"y":875,"width":69,"height":70},"offset":{"x":0,"y":0},"originalSize":{"width":69,"height":70},"rotated":true,"capInsets":[0,0,0,0],"packable":true,"pixelsToUnit":100,"pivot":{"x":0.5,"y":0.5},"meshType":0}],[0],0,[0],[0],[0]],[[{"name":"auto-atlas","spriteFrames":["06-head","614f0d15-b393-475b-a7ef-bb4e579b412b@f9941","03-body","5e8f4f07-86e5-4931-b71a-9a0efaf1a8ac@f9941","07-head1","207e2413-5d54-4661-9ff4-f0d4843b39ff@f9941","05-ear2","da8402d7-e59a-443c-8fd4-c8fb91dc2375@f9941","01-arm1","cc346610-4f91-4639-b0a5-cff862e0212b@f9941","02-arm2","58072c2e-c4c0-4098-ac0f-e019a6eabca0@f9941","04-ear1","5d45a942-a145-40c9-92c8-ea074f05c3f6@f9941","08-leg1","fbaa4b2c-1452-41fd-9454-0f0909d7d2c8@f9941","09-leg2","cd756224-56af-4b97-b263-3e077f7eaf7a@f9941","10-tail","f1d34df9-88e0-46fa-9ecf-3cbfcc838574@f9941"]}],[1],0,[],[],[]],[[{"name":"01-arm1","rect":{"x":753,"y":717,"width":132,"height":152},"offset":{"x":0,"y":0},"originalSize":{"width":132,"height":152},"rotated":false,"capInsets":[0,0,0,0],"packable":true,"pixelsToUnit":100,"pivot":{"x":0.5,"y":0.5},"meshType":0}],[0],0,[0],[0],[0]],[[{"name":"09-leg2","rect":{"x":607,"y":733,"width":108,"height":97},"offset":{"x":0,"y":0},"originalSize":{"width":108,"height":97},"rotated":true,"capInsets":[0,0,0,0],"packable":true,"pixelsToUnit":100,"pivot":{"x":0.5,"y":0.5},"meshType":0}],[0],0,[0],[0],[0]],[[{"name":"05-ear2","rect":{"x":406,"y":848,"width":168,"height":178},"offset":{"x":0,"y":0},"originalSize":{"width":168,"height":178},"rotated":true,"capInsets":[0,0,0,0],"packable":true,"pixelsToUnit":100,"pivot":{"x":0.5,"y":0.5},"meshType":0}],[0],0,[0],[0],[0]],[[{"name":"10-tail","rect":{"x":749,"y":950,"width":69,"height":70},"offset":{"x":0,"y":0},"originalSize":{"width":69,"height":70},"rotated":false,"capInsets":[0,0,0,0],"packable":true,"pixelsToUnit":100,"pivot":{"x":0.5,"y":0.5},"meshType":0}],[0],0,[0],[0],[0]],[[{"name":"08-leg1","rect":{"x":398,"y":733,"width":109,"height":100},"offset":{"x":0,"y":0},"originalSize":{"width":109,"height":100},"rotated":true,"capInsets":[0,0,0,0],"packable":true,"pixelsToUnit":100,"pivot":{"x":0.5,"y":0.5},"meshType":0}],[0],0,[0],[0],[0]]]]
